{
  "listings": [
    {
      "id": "d223d03f-9d6e-4d08-a506-ab20028abfff",
      "title": "Mountain Bike – Lightweight Frame, Smooth Ride",
      "briefDescription": "Well-maintained mountain bike, great for city rides or trails.",
      "description": "This mountain bike is in good condition and rides smoothly on both paved roads and light trails. The lightweight frame makes it easy to handle, while the reliable brakes and gears provide a comfortable and safe riding experience. Ideal for daily commuting, exercise, or weekend adventures. Recently checked and ready to ride.",
      "price": "600",
      "category": "Hobbies",
      "type": "Selling",
      "location": "Mikkeli",
      "date": "18/12/2025, 11:08",
      "favorites": [],
      "image": "bicycle.png",
      "sellerName": "Topias",
      "sellerId": "1766014892068"
    },
    {
      "id": "0657b258-36fb-44ac-8570-f8e58c6e1825",
      "title": "Comfortable Wooden Chair for Home or Office",
      "briefDescription": "Sturdy wooden chair with a simple, modern design.",
      "description": "A solid wooden chair that fits perfectly in a dining room, home office, or bedroom. The chair is stable, comfortable, and well-balanced, with minimal signs of use. Its clean design works with most interior styles, making it a practical and stylish addition to your space.",
      "price": "200",
      "category": "Furniture",
      "type": "Selling",
      "location": "Mikkeli",
      "date": "18/12/2025, 11:08",
      "favorites": [],
      "image": "chair.png",
      "sellerName": "Topias",
      "sellerId": "1766014892068"
    },
    {
      "id": "7369fae6-7b69-4c12-a9c0-e9d70cd3d23e",
      "title": "Men’s Winter Jacket – Warm and Stylish",
      "briefDescription": "Warm jacket in good condition, perfect for cold weather.",
      "description": "This winter jacket provides excellent warmth while maintaining a clean and stylish look. It features a comfortable fit, durable zipper, and well-insulated lining to keep you warm on chilly days. Lightly worn and well cared for, making it a great choice for everyday winter use.",
      "price": "50",
      "category": "Clothes",
      "type": "Selling",
      "location": "Mikkeli",
      "date": "18/12/2025, 11:08",
      "favorites": [],
      "image": "jacket.png",
      "sellerName": "Topias",
      "sellerId": "1766014892068"
    },
    {
      "id": "90785fef-4d1e-4e47-8b74-802d851d012e",
      "title": "Classic Blue Jeans – Comfortable Fit",
      "briefDescription": "Casual blue jeans with a relaxed, comfortable feel.",
      "description": "A pair of classic blue jeans suitable for everyday wear. The denim is durable yet comfortable, offering a relaxed fit without feeling loose. These jeans have been lightly worn and are still in great condition, perfect for casual outings or daily use.",
      "price": "0",
      "category": "Clothes",
      "type": "Giving Away",
      "location": "Mikkeli",
      "date": "18/12/2025, 11:09",
      "favorites": [],
      "image": "jeans.png",
      "sellerName": "Topias",
      "sellerId": "1766014892068"
    },
    {
      "id": "02ac042f-cfcc-4796-8a84-6799fd782207",
      "title": "Flat Screen TV – Clear Picture & Great Sound",
      "briefDescription": "Well-functioning TV with clear display and sound.",
      "description": "This flat screen TV delivers a sharp picture and clear audio, making it perfect for movies, shows, and gaming. It has been well maintained and works perfectly with no issues. Ideal for a living room, bedroom, or office setup. Ready for immediate use.",
      "price": "400",
      "category": "Electronics",
      "type": "Selling",
      "location": "Mikkeli",
      "date": "18/12/2025, 11:09",
      "favorites": [],
      "image": "shoes.png",
      "sellerName": "Topias",
      "sellerId": "1766014892068"
    },
    {
      "id": "58a9c22c-17ba-42f8-9657-cd8a8bb54370",
      "title": "Casual Sneakers – Clean and Comfortable",
      "briefDescription": "Comfortable sneakers, ideal for daily wear.",
      "description": "These casual sneakers are lightweight, comfortable, and easy to wear throughout the day. They provide good support for walking and everyday activities. The shoes are in good condition with normal signs of use and are a great option for anyone looking for reliable daily footwear.",
      "price": "50",
      "category": "Sports and Outdoors",
      "type": "Selling",
      "location": "Mikkeli",
      "date": "18/12/2025, 11:10",
      "favorites": [],
      "image": "tv.png",
      "sellerName": "Topias",
      "sellerId": "1766014892068"
    }
  ],
  "users": [
    {
      "id": "1765970309406",
      "fullname": "mohammed",
      "email": "a@gmail.com",
      "password": "m123456"
    },
    {
      "id": "1765996989459",
      "fullname": "mohammed",
      "email": "mohammed@example.com",
      "password": "m123456"
    },
    {
      "id": "1765998802409",
      "fullname": "ali",
      "email": "ali@gmail.com",
      "password": "a123"
    },
    {
      "id": "1766004134786",
      "fullname": "moi",
      "email": "moi@gmail.com",
      "password": "12"
    },
    {
      "id": "1766004230076",
      "fullname": "mmmm",
      "email": "mmm@gmail.com",
      "password": "111111"
    },
    {
      "id": "1766004427095",
      "fullname": "aaaaa",
      "email": "aaa@gmail.com",
      "password": "222"
    }
  ]
}